fastrec/GraphSimRec.py
fastrec/RecAPI.py
fastrec/__init__.py
fastrec/fastrec-deploy
fastrec/geosim.py
fastrec/torchmodels.py
fastrec-0.0.4.data/scripts/fastrec-deploy
fastrec-0.0.4.dist-info/METADATA
fastrec-0.0.4.dist-info/WHEEL
fastrec-0.0.4.dist-info/dependency_links.txt
fastrec-0.0.4.dist-info/top_level.txt
fastrec-0.0.4.dist-info/RECORD
