Metadata-Version: 2.1
Name: fastrec
Version: 0.0.4
Summary: Rapidly deployed gnn based recommender
Home-page: https://github.com/devinjdangelo/FastRec
Author: Devin DAngelo
License: UNKNOWN
Keywords: recommender graph neural network gnn deployment deploy
Platform: UNKNOWN
Requires-Dist: fastapi
Requires-Dist: uvicorn
Requires-Dist: tqdm
Requires-Dist: pandas
